dstrf/__init__.py
dstrf/_crossvalidation.py
dstrf/_dstrf.py
dstrf/_fastac.py
dstrf/_model.py
dstrf/opt.cp37-win_amd64.pyd
dstrf/test_dstrf.py
dstrf/dsyevh3C/__init__.py
dstrf/dsyevh3C/dsyevh3py.cp37-win_amd64.pyd
dstrf-0.2.dist-info/LICENSE.txt
dstrf-0.2.dist-info/METADATA
dstrf-0.2.dist-info/WHEEL
dstrf-0.2.dist-info/top_level.txt
dstrf-0.2.dist-info/RECORD
