Metadata-Version: 2.1
Name: dstrf
Version: 0.2
Summary: MEG/EEG source localization tool
Home-page: https://github.com/proloyd/DstRF
Author: Proloy DAS
Author-email: proloy@umd.com
License: apache 2.0
Project-URL: Source Code, https://github.com/proloyd/DstRF/archive/0.2.tar.gz
Platform: UNKNOWN
Requires-Python: >=3.6
Requires-Dist: eelbrain
